{
  "openapi": "3.0.1",
  "info": {
    "title": "insuranceWebApi",
    "version": "1.0"
  },
  "paths": {
    "/api/Calculation/Get": {
      "get": {
        "tags": [
          "Calculation"
        ],
        "responses": {
          "200": {
            "description": "OK"
          }
        }
      }
    },
    "/api/Calculation/Get/{id}": {
      "get": {
        "tags": [
          "Calculation"
        ],
        "parameters": [
          {
            "name": "id",
            "in": "path",
            "required": true,
            "schema": {
              "type": "integer",
              "format": "int32"
            }
          }
        ],
        "responses": {
          "200": {
            "description": "OK"
          }
        }
      }
    },
    "/api/Customer/Get": {
      "get": {
        "tags": [
          "Customer"
        ],
        "responses": {
          "200": {
            "description": "OK"
          }
        }
      }
    },
    "/api/Customer/Get/{id}": {
      "get": {
        "tags": [
          "Customer"
        ],
        "parameters": [
          {
            "name": "id",
            "in": "path",
            "required": true,
            "schema": {
              "type": "integer",
              "format": "int32"
            }
          }
        ],
        "responses": {
          "200": {
            "description": "OK"
          }
        }
      }
    },
    "/api/Policy/Get": {
      "get": {
        "tags": [
          "Policy"
        ],
        "responses": {
          "200": {
            "description": "OK"
          }
        }
      }
    },
    "/api/Policy/Get/{id}": {
      "get": {
        "tags": [
          "Policy"
        ],
        "parameters": [
          {
            "name": "id",
            "in": "path",
            "required": true,
            "schema": {
              "type": "integer",
              "format": "int32"
            }
          }
        ],
        "responses": {
          "200": {
            "description": "OK"
          }
        }
      }
    }
  },
  "components": { }
}